notifical/__init__.py
notifical/config.py
notifical/daemon.py
notifical/feed.py
notifical-0.2.0.dist-info/LICENSE
notifical-0.2.0.dist-info/METADATA
notifical-0.2.0.dist-info/WHEEL
notifical-0.2.0.dist-info/RECORD
